recipe_searchers/AllRecipes.py
recipe_searchers/BBCCoUk.py
recipe_searchers/BBCGoodFood.py
recipe_searchers/BonAppetit.py
recipe_searchers/Food.py
recipe_searchers/HostTheToast.py
recipe_searchers/JamieOliver.py
recipe_searchers/NyTimes.py
recipe_searchers/TheWoksOfLife.py
recipe_searchers/__init__.py
recipe_searchers/__version__.py
recipe_searchers/_abstract.py
recipe_searchers/_logger.py
recipe_searchers/_result.py
recipe_searchers-0.0.7.dist-info/LICENSE
recipe_searchers-0.0.7.dist-info/METADATA
recipe_searchers-0.0.7.dist-info/WHEEL
recipe_searchers-0.0.7.dist-info/top_level.txt
recipe_searchers-0.0.7.dist-info/RECORD
