Metadata-Version: 2.1
Name: recipe-searchers
Version: 0.0.7
Summary: A webscraping package to search for recipes URL's
Home-page: https://github.com/MichielMag/recipe-searchers
Author: Michiel K
Author-email: michieL_m@live.nl
License: UNKNOWN
Platform: UNKNOWN
Classifier: Programming Language :: Python :: 3
Classifier: License :: OSI Approved :: MIT License
Classifier: Operating System :: OS Independent
Requires-Python: >=3.6
Requires-Dist: bs4
Requires-Dist: tldextract
